odoo/addons/shopfloor_reception_vendor_packaging/README.rst
odoo/addons/shopfloor_reception_vendor_packaging/__init__.py
odoo/addons/shopfloor_reception_vendor_packaging/__manifest__.py
odoo/addons/shopfloor_reception_vendor_packaging/post_init_hook.py
odoo/addons/shopfloor_reception_vendor_packaging/i18n/it.po
odoo/addons/shopfloor_reception_vendor_packaging/i18n/shopfloor_reception_vendor_packaging.pot
odoo/addons/shopfloor_reception_vendor_packaging/readme/CONTRIBUTORS.rst
odoo/addons/shopfloor_reception_vendor_packaging/readme/DESCRIPTION.rst
odoo/addons/shopfloor_reception_vendor_packaging/services/__init__.py
odoo/addons/shopfloor_reception_vendor_packaging/services/reception.py
odoo/addons/shopfloor_reception_vendor_packaging/static/description/icon.png
odoo/addons/shopfloor_reception_vendor_packaging/static/description/index.html
odoo14_addon_shopfloor_reception_vendor_packaging-14.0.1.0.1.dev3.dist-info/METADATA
odoo14_addon_shopfloor_reception_vendor_packaging-14.0.1.0.1.dev3.dist-info/WHEEL
odoo14_addon_shopfloor_reception_vendor_packaging-14.0.1.0.1.dev3.dist-info/top_level.txt
odoo14_addon_shopfloor_reception_vendor_packaging-14.0.1.0.1.dev3.dist-info/RECORD
